generator_oj_problem/__init__.py
generator_oj_problem/__main__.py
generator_oj_problem/models.py
generator_oj_problem/pipelines.py
generator_oj_problem/adapters/__init__.py
generator_oj_problem/adapters/fps/__init__.py
generator_oj_problem/adapters/fps/packer.py
generator_oj_problem/adapters/generic/__init__.py
generator_oj_problem/adapters/generic/checker.py
generator_oj_problem/adapters/generic/initializer.py
generator_oj_problem/adapters/generic/loader.py
generator_oj_problem/adapters/generic/paths.py
generator_oj_problem/adapters/hustoj/__init__.py
generator_oj_problem/generators/__init__.py
generator_oj_problem/generators/processors.py
generator_oj_problem/generators/template.py
generator_oj_problem/generators/trimmers.py
generator_oj_problem-0.0.2.dist-info/METADATA
generator_oj_problem-0.0.2.dist-info/WHEEL
generator_oj_problem-0.0.2.dist-info/entry_points.txt
generator_oj_problem-0.0.2.dist-info/top_level.txt
generator_oj_problem-0.0.2.dist-info/RECORD
