Metadata-Version: 2.1
Name: generator-oj-problem
Version: 0.0.2
Summary: A command-line tool to generate Online-Judge problem.
Home-page: https://github.com/StardustDL/generator-oj-problem
Author: StardustDL
Author-email: stardustdl@163.com
Project-URL: Source Code, https://github.com/StardustDL/generator-oj-problem
Project-URL: Changes, https://github.com/StardustDL/generator-oj-problem/releases
Project-URL: Bug Tracker, https://github.com/StardustDL/generator-oj-problem/issues
Classifier: License :: OSI Approved :: Mozilla Public License 2.0 (MPL 2.0)
Classifier: Operating System :: OS Independent
Classifier: Programming Language :: Python :: 3
Classifier: Programming Language :: Python :: 3.7
Classifier: Programming Language :: Python :: 3.8
Classifier: Programming Language :: Python :: 3.9
Classifier: Programming Language :: Python :: 3.10
Classifier: Programming Language :: Python :: 3.11
Classifier: Programming Language :: Python :: Implementation :: CPython
Classifier: Topic :: Utilities
Requires-Python: >=3.7
Requires-Dist: click (>=8.0)
Requires-Dist: PyYAML (>=6.0)
Requires-Dist: mistune (>=2.0.0)
Requires-Dist: chardet (>=5.0.0)
